{
    "frequency_range": [
        7994465562158.582,
        299792458580946.8
    ],
    "name": null,
    "eps_inf": 1.0,
    "poles": [
        [
            [
                -1186747717018349.2,
                1500894658830146.0
            ],
            [
                14604089794926.691,
                -4338830401247255.0
            ]
        ],
        [
            [
                -4717665656375227.0,
                -9729152786055812.0
            ],
            [
                7843765854319.862,
                4.394462137649668e+16
            ]
        ]
    ],
    "type": "PoleResidue"
}